pymatchingtools/__init__.py
pymatchingtools/functions.py
pymatchingtools/matching.py
pymatchingtools/utils.py
pymatchingtools-0.1.0.dist-info/LICENSE
pymatchingtools-0.1.0.dist-info/METADATA
pymatchingtools-0.1.0.dist-info/WHEEL
pymatchingtools-0.1.0.dist-info/top_level.txt
pymatchingtools-0.1.0.dist-info/zip-safe
pymatchingtools-0.1.0.dist-info/RECORD
