Metadata-Version: 2.1
Name: pymatchingtools
Version: 0.1.0
Summary: A toolbox of common matching methods
Home-page: https://github.com/Trouvaille98/pymatchingtools
Author: Trouvaille98
Author-email: dulingzhi.0710@gmail.com
License: MIT
Keywords: causal inference,PSM,Matching,observational study,pymatchingtools,psm,propensity score,propensity score matching,balance check
Requires-Python: >=3.7
License-File: LICENSE
Requires-Dist: numpy
Requires-Dist: pandas
Requires-Dist: seaborn
Requires-Dist: matplotlib
Requires-Dist: lightgbm ==2.2.3
Requires-Dist: statsmodels
Requires-Dist: patsy
